src/__init__.py
src/cligon.py
src/terminal_colors.py
src/url_checker.py
src/url_status.py
cligon-1.0.2.dist-info/LICENSE
cligon-1.0.2.dist-info/METADATA
cligon-1.0.2.dist-info/WHEEL
cligon-1.0.2.dist-info/entry_points.txt
cligon-1.0.2.dist-info/top_level.txt
cligon-1.0.2.dist-info/RECORD
