Metadata-Version: 2.1
Name: cligon
Version: 1.0.2
Summary: A small program to check the status of URLs
Home-page: https://github.com/rogercyyu/cligon-url-checker
Author: Roger Yu
Author-email: rogeryu27@gmail.com
License: UNKNOWN
Platform: UNKNOWN
Classifier: Programming Language :: Python :: 3
Classifier: License :: OSI Approved :: MIT License
Classifier: Operating System :: OS Independent
Requires-Python: >=3.8
Requires-Dist: appdirs (==1.4.4)
Requires-Dist: attrs (==20.3.0)
Requires-Dist: black (==20.8b1)
Requires-Dist: certifi (==2020.6.20)
Requires-Dist: cfgv (==3.2.0)
Requires-Dist: chardet (==3.0.4)
Requires-Dist: click (==7.1.2)
Requires-Dist: coverage (==5.3)
Requires-Dist: distlib (==0.3.1)
Requires-Dist: filelock (==3.0.12)
Requires-Dist: flake8 (==3.8.4)
Requires-Dist: identify (==1.5.9)
Requires-Dist: idna (==2.10)
Requires-Dist: iniconfig (==1.1.1)
Requires-Dist: mccabe (==0.6.1)
Requires-Dist: mypy-extensions (==0.4.3)
Requires-Dist: nodeenv (==1.5.0)
Requires-Dist: packaging (==20.4)
Requires-Dist: pathspec (==0.8.0)
Requires-Dist: pluggy (==0.13.1)
Requires-Dist: pre-commit (==2.8.2)
Requires-Dist: py (==1.9.0)
Requires-Dist: pycodestyle (==2.6.0)
Requires-Dist: pyflakes (==2.2.0)
Requires-Dist: pyparsing (==2.4.7)
Requires-Dist: pytest (==6.1.2)
Requires-Dist: PyYAML (==5.3.1)
Requires-Dist: regex (==2020.10.28)
Requires-Dist: requests (==2.24.0)
Requires-Dist: responses (==0.12.1)
Requires-Dist: six (==1.15.0)
Requires-Dist: toml (==0.10.2)
Requires-Dist: typed-ast (==1.4.1)
Requires-Dist: typing-extensions (==3.7.4.3)
Requires-Dist: urllib3 (==1.25.11)
Requires-Dist: virtualenv (==20.1.0)
